starlette_ras_handle/__init__.py
starlette_ras_handle-1.0.2.dist-info/METADATA
starlette_ras_handle-1.0.2.dist-info/WHEEL
starlette_ras_handle-1.0.2.dist-info/licenses/LICENSE
starlette_ras_handle-1.0.2.dist-info/RECORD
