Metadata-Version: 2.4
Name: starlette-ras-handle
Version: 1.0.2
Summary: This library patches starlette, so you can handle "RuntimeError: Caught handled exception, but response already started." exception
License-Expression: MIT
License-File: LICENSE
Requires-Python: >=3.12
Requires-Dist: starlette>=0.46.2
